halluminate/__init__.py
halluminate/calls.py
halluminate-0.0.4.dist-info/METADATA
halluminate-0.0.4.dist-info/WHEEL
halluminate-0.0.4.dist-info/top_level.txt
halluminate-0.0.4.dist-info/RECORD
