Metadata-Version: 2.1
Name: halluminate
Version: 0.0.4
Summary: A package for interacting with the Halluminate API
Home-page: https://halluminate.ai
Author: Wyatt Marshall
Author-email: wyatt@halluminate.ai
Requires-Python: >=3.8
Requires-Dist: requests
